womm/__init__.py
womm/__main__.py
womm/cli.py
womm/bin/RefreshEnv.cmd
womm/commands/__init__.py
womm/commands/context.py
womm/commands/install.py
womm/commands/lint.py
womm/commands/new.py
womm/commands/setup.py
womm/commands/spell.py
womm/commands/system.py
womm/commands/template.py
womm/common/__init__.py
womm/common/imports.py
womm/common/path_resolver.py
womm/common/results.py
womm/common/security.py
womm/configs/__init__.py
womm/configs/cspell.global.json
womm/core/exceptions/__init__.py
womm/core/exceptions/installation/__init__.py
womm/core/exceptions/installation/installation_exceptions.py
womm/core/exceptions/installation/uninstallation_exceptions.py
womm/core/exceptions/system/__init__.py
womm/core/exceptions/system/user_path_exceptions.py
womm/core/managers/__init__.py
womm/core/managers/context/__init__.py
womm/core/managers/context/managers/__init__.py
womm/core/managers/context/managers/backup_manager.py
womm/core/managers/context/managers/context_menu.py
womm/core/managers/context/managers/icon_manager.py
womm/core/managers/context/managers/script_detector.py
womm/core/managers/context/utils/__init__.py
womm/core/managers/context/utils/context_parameters.py
womm/core/managers/context/utils/registry_utils.py
womm/core/managers/context/utils/validation.py
womm/core/managers/dependencies/__init__.py
womm/core/managers/dependencies/dev_tools_manager.py
womm/core/managers/dependencies/package_manager.py
womm/core/managers/dependencies/runtime_manager.py
womm/core/managers/installation/__init__.py
womm/core/managers/installation/installation_manager.py
womm/core/managers/installation/uninstallation_manager.py
womm/core/managers/lint/__init__.py
womm/core/managers/lint/lint_manager.py
womm/core/managers/project/__init__.py
womm/core/managers/project/project_manager.py
womm/core/managers/project/creation/__init__.py
womm/core/managers/project/creation/javascript_project_manager.py
womm/core/managers/project/creation/project_creator.py
works_on_my_machine-2.6.8.dist-info/licenses/LICENSE
works_on_my_machine-2.6.8.dist-info/METADATA
works_on_my_machine-2.6.8.dist-info/WHEEL
works_on_my_machine-2.6.8.dist-info/entry_points.txt
works_on_my_machine-2.6.8.dist-info/top_level.txt
works_on_my_machine-2.6.8.dist-info/RECORD
